dakota_wheel/__init__.py
dakota_wheel-0.0.2.data/scripts/dakota
dakota_wheel-0.0.2.data/platlib/dakota/environment/__init__.py
dakota_wheel-0.0.2.data/platlib/dakota/environment/environment.cpython-38-x86_64-linux-gnu.so
dakota_wheel-0.0.2.dist-info/METADATA
dakota_wheel-0.0.2.dist-info/WHEEL
dakota_wheel-0.0.2.dist-info/entry_points.txt
dakota_wheel-0.0.2.dist-info/RECORD
