Metadata-Version: 2.1
Name: dakota_wheel
Version: 0.0.2
Summary: Dakota wheel
